browlite/__init__.py
browlite/config.py
browlite/main.py
browlite/utils.py
browlite/resources/icons/back.png
browlite/resources/icons/bing.png
browlite/resources/icons/duckduckgo.png
browlite/resources/icons/ecosia.png
browlite/resources/icons/forward.png
browlite/resources/icons/google.png
browlite/resources/icons/home.png
browlite/resources/icons/refresh.png
browlite/resources/icons/yahoo.png
browlite/resources/styles/dark.css
browlite/resources/styles/light.css
browlite-1.0.1.dist-info/LICENSE
browlite-1.0.1.dist-info/METADATA
browlite-1.0.1.dist-info/WHEEL
browlite-1.0.1.dist-info/entry_points.txt
browlite-1.0.1.dist-info/top_level.txt
browlite-1.0.1.dist-info/RECORD
