Metadata-Version: 2.1
Name: browlite
Version: 1.0.1
Summary: Navegador minimalista leve e rápido com foco em privacidade
Home-page: https://github.com/PineRootLabs/Browlite
Author: PineRootLabs
Author-email: DevDark249@gmail.com
License: MIT
Keywords: browser navegador minimalista python pyqt
Classifier: Development Status :: 4 - Beta
Classifier: Intended Audience :: End Users/Desktop
Classifier: License :: OSI Approved :: MIT License
Classifier: Programming Language :: Python :: 3
Classifier: Programming Language :: Python :: 3.7
Classifier: Programming Language :: Python :: 3.8
Classifier: Programming Language :: Python :: 3.9
Classifier: Operating System :: OS Independent
Classifier: Environment :: X11 Applications :: Qt
Classifier: Topic :: Internet :: WWW/HTTP :: Browsers
License-File: LICENSE
Requires-Dist: PyQt5>=5.15.4
Requires-Dist: PyQtWebEngine>=5.15.5
